{
    "initializationUrls": [
        "terria"
    ],
    "parameters": {
        "bingMapsKey": "AkaOmRFtjAb71cXgLwAGtLbj2RpkPKtVqAIroFQsocfurCBILxIeAWPkil7hhRy_",
        "googleUrlShortenerKey": null,
        "googleAnalyticsKey": null,
        "googleAnalyticsOptions": null,

        "autoPlay": false,
        
        "developerAttribution": {
            "text": "National Computational Infrastructure (NCI)",
            "link": "https://github.com/nci/gsky"
        },
        "appName": "Terria Map - GSKY Docker",

        "brandBarElements": [
            "",
            "<a target=\"_blank\" href=\"https://github.com/nci/gsky\"><img src=\"../img/logo.svg\" title=\"GSKY Docker\" /></a>",
            ""
        ],

        "supportEmail": "help@nci.org.au",
        "feedbackUrl": "https://github.com/nci/gsky/issues",

        "mobileDefaultViewerMode": "2d",
        "experimentalFeatures": true
    }
}
